[{"model": "admin.logentry", "pk": 1, "fields": {"action_time": "2025-07-23T22:33:28.096Z", "user": 1, "content_type": 13, "object_id": "F3107", "object_repr": "Room object (F3107)", "action_flag": 3, "change_message": ""}}, {"model": "admin.logentry", "pk": 2, "fields": {"action_time": "2025-07-23T22:33:30.880Z", "user": 1, "content_type": 13, "object_id": "F3106", "object_repr": "Room object (F3106)", "action_flag": 3, "change_message": ""}}, {"model": "admin.logentry", "pk": 3, "fields": {"action_time": "2025-07-23T22:33:33.835Z", "user": 1, "content_type": 13, "object_id": "F3105", "object_repr": "Room object (F3105)", "action_flag": 3, "change_message": ""}}, {"model": "admin.logentry", "pk": 4, "fields": {"action_time": "2025-07-23T22:33:36.800Z", "user": 1, "content_type": 13, "object_id": "F3104", "object_repr": "Room object (F3104)", "action_flag": 3, "change_message": ""}}, {"model": "admin.logentry", "pk": 5, "fields": {"action_time": "2025-07-23T22:33:39.956Z", "user": 1, "content_type": 13, "object_id": "F3103", "object_repr": "Room object (F3103)", "action_flag": 3, "change_message": ""}}, {"model": "admin.logentry", "pk": 6, "fields": {"action_time": "2025-07-23T22:33:43.918Z", "user": 1, "content_type": 13, "object_id": "F3102", "object_repr": "Room object (F3102)", "action_flag": 3, "change_message": ""}}, {"model": "admin.logentry", "pk": 7, "fields": {"action_time": "2025-07-23T22:33:47.125Z", "user": 1, "content_type": 13, "object_id": "F3101", "object_repr": "Room object (F3101)", "action_flag": 3, "change_message": ""}}, {"model": "admin.logentry", "pk": 8, "fields": {"action_time": "2025-07-23T22:33:52.571Z", "user": 1, "content_type": 13, "object_id": "F2107", "object_repr": "Room object (F2107)", "action_flag": 3, "change_message": ""}}, {"model": "admin.logentry", "pk": 9, "fields": {"action_time": "2025-07-23T22:33:56.013Z", "user": 1, "content_type": 13, "object_id": "F2106", "object_repr": "Room object (F2106)", "action_flag": 3, "change_message": ""}}, {"model": "admin.logentry", "pk": 10, "fields": {"action_time": "2025-07-23T22:33:58.313Z", "user": 1, "content_type": 13, "object_id": "F2105", "object_repr": "Room object (F2105)", "action_flag": 3, "change_message": ""}}, {"model": "admin.logentry", "pk": 11, "fields": {"action_time": "2025-07-23T22:34:01.165Z", "user": 1, "content_type": 13, "object_id": "F2104", "object_repr": "Room object (F2104)", "action_flag": 3, "change_message": ""}}, {"model": "admin.logentry", "pk": 12, "fields": {"action_time": "2025-07-23T22:34:04.510Z", "user": 1, "content_type": 13, "object_id": "F2103", "object_repr": "Room object (F2103)", "action_flag": 3, "change_message": ""}}, {"model": "admin.logentry", "pk": 13, "fields": {"action_time": "2025-07-23T22:34:07.068Z", "user": 1, "content_type": 13, "object_id": "F2102", "object_repr": "Room object (F2102)", "action_flag": 3, "change_message": ""}}, {"model": "admin.logentry", "pk": 14, "fields": {"action_time": "2025-07-23T22:34:09.744Z", "user": 1, "content_type": 13, "object_id": "F2101", "object_repr": "Room object (F2101)", "action_flag": 3, "change_message": ""}}, {"model": "admin.logentry", "pk": 15, "fields": {"action_time": "2025-07-23T22:34:12.357Z", "user": 1, "content_type": 13, "object_id": "F1107", "object_repr": "Room object (F1107)", "action_flag": 3, "change_message": ""}}, {"model": "admin.logentry", "pk": 16, "fields": {"action_time": "2025-07-23T22:34:15.281Z", "user": 1, "content_type": 13, "object_id": "F1106", "object_repr": "Room object (F1106)", "action_flag": 3, "change_message": ""}}, {"model": "admin.logentry", "pk": 17, "fields": {"action_time": "2025-07-23T22:34:18.595Z", "user": 1, "content_type": 13, "object_id": "F1105", "object_repr": "Room object (F1105)", "action_flag": 3, "change_message": ""}}, {"model": "admin.logentry", "pk": 18, "fields": {"action_time": "2025-07-23T22:34:21.310Z", "user": 1, "content_type": 13, "object_id": "F1104", "object_repr": "Room object (F1104)", "action_flag": 3, "change_message": ""}}, {"model": "admin.logentry", "pk": 19, "fields": {"action_time": "2025-07-23T22:34:23.722Z", "user": 1, "content_type": 13, "object_id": "F1103", "object_repr": "Room object (F1103)", "action_flag": 3, "change_message": ""}}, {"model": "admin.logentry", "pk": 20, "fields": {"action_time": "2025-07-23T22:34:26.280Z", "user": 1, "content_type": 13, "object_id": "F1102", "object_repr": "Room object (F1102)", "action_flag": 3, "change_message": ""}}, {"model": "admin.logentry", "pk": 21, "fields": {"action_time": "2025-07-23T22:34:29.031Z", "user": 1, "content_type": 13, "object_id": "F1101", "object_repr": "Room object (F1101)", "action_flag": 3, "change_message": ""}}, {"model": "admin.logentry", "pk": 22, "fields": {"action_time": "2025-07-23T22:35:29.723Z", "user": 1, "content_type": 13, "object_id": "F1101", "object_repr": "Room object (F1101)", "action_flag": 3, "change_message": ""}}, {"model": "admin.logentry", "pk": 23, "fields": {"action_time": "2025-07-24T00:01:06.244Z", "user": 1, "content_type": 9, "object_id": "HD0001", "object_repr": "Invoice object (HD0001)", "action_flag": 2, "change_message": "[{\"changed\": {\"fields\": [\"Trang thai\"]}}]"}}, {"model": "admin.logentry", "pk": 24, "fields": {"action_time": "2025-07-24T01:04:20.200Z", "user": 1, "content_type": 14, "object_id": "SDDV0004", "object_repr": "ServiceUsage object (SDDV0004)", "action_flag": 2, "change_message": "[{\"changed\": {\"fields\": [\"Ma nhan vien\"]}}]"}}, {"model": "admin.logentry", "pk": 25, "fields": {"action_time": "2025-07-24T01:05:12.359Z", "user": 1, "content_type": 14, "object_id": "SDDV0003", "object_repr": "ServiceUsage object (SDDV0003)", "action_flag": 2, "change_message": "[{\"changed\": {\"fields\": [\"Ma nhan vien\"]}}]"}}, {"model": "admin.logentry", "pk": 26, "fields": {"action_time": "2025-07-24T01:05:31.817Z", "user": 1, "content_type": 14, "object_id": "SDDV0002", "object_repr": "ServiceUsage object (SDDV0002)", "action_flag": 2, "change_message": "[{\"changed\": {\"fields\": [\"Ma nhan vien\"]}}]"}}, {"model": "admin.logentry", "pk": 27, "fields": {"action_time": "2025-07-24T01:05:43.429Z", "user": 1, "content_type": 14, "object_id": "SDDV0001", "object_repr": "ServiceUsage object (SDDV0001)", "action_flag": 2, "change_message": "[{\"changed\": {\"fields\": [\"Ma nhan vien\"]}}]"}}, {"model": "auth.permission", "pk": 1, "fields": {"name": "Can add log entry", "content_type": 1, "codename": "add_logentry"}}, {"model": "auth.permission", "pk": 2, "fields": {"name": "Can change log entry", "content_type": 1, "codename": "change_logentry"}}, {"model": "auth.permission", "pk": 3, "fields": {"name": "Can delete log entry", "content_type": 1, "codename": "delete_logentry"}}, {"model": "auth.permission", "pk": 4, "fields": {"name": "Can view log entry", "content_type": 1, "codename": "view_logentry"}}, {"model": "auth.permission", "pk": 5, "fields": {"name": "Can add permission", "content_type": 2, "codename": "add_permission"}}, {"model": "auth.permission", "pk": 6, "fields": {"name": "Can change permission", "content_type": 2, "codename": "change_permission"}}, {"model": "auth.permission", "pk": 7, "fields": {"name": "Can delete permission", "content_type": 2, "codename": "delete_permission"}}, {"model": "auth.permission", "pk": 8, "fields": {"name": "Can view permission", "content_type": 2, "codename": "view_permission"}}, {"model": "auth.permission", "pk": 9, "fields": {"name": "Can add group", "content_type": 3, "codename": "add_group"}}, {"model": "auth.permission", "pk": 10, "fields": {"name": "Can change group", "content_type": 3, "codename": "change_group"}}, {"model": "auth.permission", "pk": 11, "fields": {"name": "Can delete group", "content_type": 3, "codename": "delete_group"}}, {"model": "auth.permission", "pk": 12, "fields": {"name": "Can view group", "content_type": 3, "codename": "view_group"}}, {"model": "auth.permission", "pk": 13, "fields": {"name": "Can add user", "content_type": 4, "codename": "add_user"}}, {"model": "auth.permission", "pk": 14, "fields": {"name": "Can change user", "content_type": 4, "codename": "change_user"}}, {"model": "auth.permission", "pk": 15, "fields": {"name": "Can delete user", "content_type": 4, "codename": "delete_user"}}, {"model": "auth.permission", "pk": 16, "fields": {"name": "Can view user", "content_type": 4, "codename": "view_user"}}, {"model": "auth.permission", "pk": 17, "fields": {"name": "Can add content type", "content_type": 5, "codename": "add_contenttype"}}, {"model": "auth.permission", "pk": 18, "fields": {"name": "Can change content type", "content_type": 5, "codename": "change_contenttype"}}, {"model": "auth.permission", "pk": 19, "fields": {"name": "Can delete content type", "content_type": 5, "codename": "delete_contenttype"}}, {"model": "auth.permission", "pk": 20, "fields": {"name": "Can view content type", "content_type": 5, "codename": "view_contenttype"}}, {"model": "auth.permission", "pk": 21, "fields": {"name": "Can add session", "content_type": 6, "codename": "add_session"}}, {"model": "auth.permission", "pk": 22, "fields": {"name": "Can change session", "content_type": 6, "codename": "change_session"}}, {"model": "auth.permission", "pk": 23, "fields": {"name": "Can delete session", "content_type": 6, "codename": "delete_session"}}, {"model": "auth.permission", "pk": 24, "fields": {"name": "Can view session", "content_type": 6, "codename": "view_session"}}, {"model": "auth.permission", "pk": 25, "fields": {"name": "Can add code counter", "content_type": 7, "codename": "add_codecounter"}}, {"model": "auth.permission", "pk": 26, "fields": {"name": "Can change code counter", "content_type": 7, "codename": "change_codecounter"}}, {"model": "auth.permission", "pk": 27, "fields": {"name": "Can delete code counter", "content_type": 7, "codename": "delete_codecounter"}}, {"model": "auth.permission", "pk": 28, "fields": {"name": "Can view code counter", "content_type": 7, "codename": "view_codecounter"}}, {"model": "auth.permission", "pk": 29, "fields": {"name": "Can add customer", "content_type": 8, "codename": "add_customer"}}, {"model": "auth.permission", "pk": 30, "fields": {"name": "Can change customer", "content_type": 8, "codename": "change_customer"}}, {"model": "auth.permission", "pk": 31, "fields": {"name": "Can delete customer", "content_type": 8, "codename": "delete_customer"}}, {"model": "auth.permission", "pk": 32, "fields": {"name": "Can view customer", "content_type": 8, "codename": "view_customer"}}, {"model": "auth.permission", "pk": 33, "fields": {"name": "Can add invoice", "content_type": 9, "codename": "add_invoice"}}, {"model": "auth.permission", "pk": 34, "fields": {"name": "Can change invoice", "content_type": 9, "codename": "change_invoice"}}, {"model": "auth.permission", "pk": 35, "fields": {"name": "Can delete invoice", "content_type": 9, "codename": "delete_invoice"}}, {"model": "auth.permission", "pk": 36, "fields": {"name": "Can view invoice", "content_type": 9, "codename": "view_invoice"}}, {"model": "auth.permission", "pk": 37, "fields": {"name": "Can add room type", "content_type": 10, "codename": "add_roomtype"}}, {"model": "auth.permission", "pk": 38, "fields": {"name": "Can change room type", "content_type": 10, "codename": "change_roomtype"}}, {"model": "auth.permission", "pk": 39, "fields": {"name": "Can delete room type", "content_type": 10, "codename": "delete_roomtype"}}, {"model": "auth.permission", "pk": 40, "fields": {"name": "Can view room type", "content_type": 10, "codename": "view_roomtype"}}, {"model": "auth.permission", "pk": 41, "fields": {"name": "Can add service", "content_type": 11, "codename": "add_service"}}, {"model": "auth.permission", "pk": 42, "fields": {"name": "Can change service", "content_type": 11, "codename": "change_service"}}, {"model": "auth.permission", "pk": 43, "fields": {"name": "Can delete service", "content_type": 11, "codename": "delete_service"}}, {"model": "auth.permission", "pk": 44, "fields": {"name": "Can view service", "content_type": 11, "codename": "view_service"}}, {"model": "auth.permission", "pk": 45, "fields": {"name": "Can add staff", "content_type": 12, "codename": "add_staff"}}, {"model": "auth.permission", "pk": 46, "fields": {"name": "Can change staff", "content_type": 12, "codename": "change_staff"}}, {"model": "auth.permission", "pk": 47, "fields": {"name": "Can delete staff", "content_type": 12, "codename": "delete_staff"}}, {"model": "auth.permission", "pk": 48, "fields": {"name": "Can view staff", "content_type": 12, "codename": "view_staff"}}, {"model": "auth.permission", "pk": 49, "fields": {"name": "Can add room", "content_type": 13, "codename": "add_room"}}, {"model": "auth.permission", "pk": 50, "fields": {"name": "Can change room", "content_type": 13, "codename": "change_room"}}, {"model": "auth.permission", "pk": 51, "fields": {"name": "Can delete room", "content_type": 13, "codename": "delete_room"}}, {"model": "auth.permission", "pk": 52, "fields": {"name": "Can view room", "content_type": 13, "codename": "view_room"}}, {"model": "auth.permission", "pk": 53, "fields": {"name": "Can add service usage", "content_type": 14, "codename": "add_serviceusage"}}, {"model": "auth.permission", "pk": 54, "fields": {"name": "Can change service usage", "content_type": 14, "codename": "change_serviceusage"}}, {"model": "auth.permission", "pk": 55, "fields": {"name": "Can delete service usage", "content_type": 14, "codename": "delete_serviceusage"}}, {"model": "auth.permission", "pk": 56, "fields": {"name": "Can view service usage", "content_type": 14, "codename": "view_serviceusage"}}, {"model": "auth.permission", "pk": 57, "fields": {"name": "Can add account", "content_type": 15, "codename": "add_account"}}, {"model": "auth.permission", "pk": 58, "fields": {"name": "Can change account", "content_type": 15, "codename": "change_account"}}, {"model": "auth.permission", "pk": 59, "fields": {"name": "Can delete account", "content_type": 15, "codename": "delete_account"}}, {"model": "auth.permission", "pk": 60, "fields": {"name": "Can view account", "content_type": 15, "codename": "view_account"}}, {"model": "auth.permission", "pk": 61, "fields": {"name": "Can add rent", "content_type": 16, "codename": "add_rent"}}, {"model": "auth.permission", "pk": 62, "fields": {"name": "Can change rent", "content_type": 16, "codename": "change_rent"}}, {"model": "auth.permission", "pk": 63, "fields": {"name": "Can delete rent", "content_type": 16, "codename": "delete_rent"}}, {"model": "auth.permission", "pk": 64, "fields": {"name": "Can view rent", "content_type": 16, "codename": "view_rent"}}, {"model": "auth.user", "pk": 1, "fields": {"password": "pbkdf2_sha256$1000000$1inskyA6O1rkx1gx4dJsLu$uD9kXu8xDbx0mPMHX853MA6SNY04wMgxKv8IA6oJU2E=", "last_login": "2025-07-23T20:40:27.470Z", "is_superuser": true, "username": "admin", "first_name": "", "last_name": "", "email": "admin@example.com", "is_staff": true, "is_active": true, "date_joined": "2025-07-22T09:33:18.382Z", "groups": [], "user_permissions": []}}, {"model": "contenttypes.contenttype", "pk": 1, "fields": {"app_label": "admin", "model": "logentry"}}, {"model": "contenttypes.contenttype", "pk": 2, "fields": {"app_label": "auth", "model": "permission"}}, {"model": "contenttypes.contenttype", "pk": 3, "fields": {"app_label": "auth", "model": "group"}}, {"model": "contenttypes.contenttype", "pk": 4, "fields": {"app_label": "auth", "model": "user"}}, {"model": "contenttypes.contenttype", "pk": 5, "fields": {"app_label": "contenttypes", "model": "contenttype"}}, {"model": "contenttypes.contenttype", "pk": 6, "fields": {"app_label": "sessions", "model": "session"}}, {"model": "contenttypes.contenttype", "pk": 7, "fields": {"app_label": "app", "model": "codecounter"}}, {"model": "contenttypes.contenttype", "pk": 8, "fields": {"app_label": "app", "model": "customer"}}, {"model": "contenttypes.contenttype", "pk": 9, "fields": {"app_label": "app", "model": "invoice"}}, {"model": "contenttypes.contenttype", "pk": 10, "fields": {"app_label": "app", "model": "roomtype"}}, {"model": "contenttypes.contenttype", "pk": 11, "fields": {"app_label": "app", "model": "service"}}, {"model": "contenttypes.contenttype", "pk": 12, "fields": {"app_label": "app", "model": "staff"}}, {"model": "contenttypes.contenttype", "pk": 13, "fields": {"app_label": "app", "model": "room"}}, {"model": "contenttypes.contenttype", "pk": 14, "fields": {"app_label": "app", "model": "serviceusage"}}, {"model": "contenttypes.contenttype", "pk": 15, "fields": {"app_label": "app", "model": "account"}}, {"model": "contenttypes.contenttype", "pk": 16, "fields": {"app_label": "app", "model": "rent"}}, {"model": "sessions.session", "pk": "3xzztxqlpjvx0ncxp01n7jsl6t0zgrwg", "fields": {"session_data": ".eJxVjDsOwyAQBe9CHaGFxQukTO8zIL7BSYQlY1dR7h4huUjaNzPvzZw_9uqOnje3JHZlgl1-t-DjM7cB0sO3-8rj2vZtCXwo_KSdz2vKr9vp_h1U3-uopYJsfMA4AYCRqWQyBQyBpZikDRZJKCUm0oSQSYcYETGhEkSgC_t8AcWmNq8:1ueWt2:jgTpFZ9upvQwT54G8O82-MS2GrGyO4TCDmIkFWPyXfA", "expire_date": "2025-08-06T10:39:48.093Z"}}, {"model": "sessions.session", "pk": "pvifhmy6tflqdb4684dsqi1v1vl9yd5e", "fields": {"session_data": ".eJxVjDsOwyAQBe9CHaGFxQukTO8zIL7BSYQlY1dR7h4huUjaNzPvzZw_9uqOnje3JHZlgl1-t-DjM7cB0sO3-8rj2vZtCXwo_KSdz2vKr9vp_h1U3-uopYJsfMA4AYCRqWQyBQyBpZikDRZJKCUm0oSQSYcYETGhEkSgC_t8AcWmNq8:1uegGJ:5OdDVuI_ebafNz_VxaZ1jxIo4kckH2fBWzjz_BbcqcE", "expire_date": "2025-08-06T20:40:27.473Z"}}, {"model": "sessions.session", "pk": "s4yxs7ab0c9z4glvthd437k8so6lw6xh", "fields": {"session_data": ".eJxVjDsOwyAQBe9CHaGFxQukTO8zIL7BSYQlY1dR7h4huUjaNzPvzZw_9uqOnje3JHZlgl1-t-DjM7cB0sO3-8rj2vZtCXwo_KSdz2vKr9vp_h1U3-uopYJsfMA4AYCRqWQyBQyBpZikDRZJKCUm0oSQSYcYETGhEkSgC_t8AcWmNq8:1ueWt1:HmbWmWy__RnUZRUNkxJ0UMCJz_mSzoUsYriwMMI2nWc", "expire_date": "2025-08-06T10:39:47.815Z"}}, {"model": "sessions.session", "pk": "vmu5j3g5smqkotixusp9erslen8mkhwv", "fields": {"session_data": ".eJxVjDsOwyAQBe9CHaGFxQukTO8zIL7BSYQlY1dR7h4huUjaNzPvzZw_9uqOnje3JHZlgl1-t-DjM7cB0sO3-8rj2vZtCXwo_KSdz2vKr9vp_h1U3-uopYJsfMA4AYCRqWQyBQyBpZikDRZJKCUm0oSQSYcYETGhEkSgC_t8AcWmNq8:1ue9O6:nDEl8izZH8GBBWn9QyyjK4tipCj6V5VO2pMt7W8yxqU", "expire_date": "2025-08-05T09:34:18.500Z"}}, {"model": "app.codecounter", "pk": 1, "fields": {"key": "Staff", "last_number": 8}}, {"model": "app.codecounter", "pk": 2, "fields": {"key": "Admin", "last_number": 2}}, {"model": "app.codecounter", "pk": 3, "fields": {"key": "RoomType", "last_number": 7}}, {"model": "app.codecounter", "pk": 4, "fields": {"key": "Service", "last_number": 8}}, {"model": "app.codecounter", "pk": 5, "fields": {"key": "Customer", "last_number": 10}}, {"model": "app.codecounter", "pk": 6, "fields": {"key": "Rent", "last_number": 1}}, {"model": "app.codecounter", "pk": 7, "fields": {"key": "ServiceUsage", "last_number": 4}}, {"model": "app.codecounter", "pk": 8, "fields": {"key": "Invoice", "last_number": 1}}, {"model": "app.staff", "pk": "AD001", "fields": {"ho_ten": "Trịnh Văn Nam", "ngay_sinh": "1987-08-18", "so_dien_thoai": "0911223344", "role": "admin"}}, {"model": "app.staff", "pk": "AD002", "fields": {"ho_ten": "Hồ Thị Thu Trang", "ngay_sinh": "1990-02-22", "so_dien_thoai": "0933445566", "role": "admin"}}, {"model": "app.staff", "pk": "NV001", "fields": {"ho_ten": "Nguyễn Văn An", "ngay_sinh": "1990-01-15", "so_dien_thoai": "0912345678", "role": "staff"}}, {"model": "app.staff", "pk": "NV002", "fields": {"ho_ten": "Trần Thị Bình", "ngay_sinh": "1992-03-21", "so_dien_thoai": "0934567890", "role": "staff"}}, {"model": "app.staff", "pk": "NV003", "fields": {"ho_ten": "Lê Văn Cường", "ngay_sinh": "1989-06-10", "so_dien_thoai": "0987654321", "role": "staff"}}, {"model": "app.staff", "pk": "NV004", "fields": {"ho_ten": "Phạm Thị Dung", "ngay_sinh": "1995-12-12", "so_dien_thoai": "0901234567", "role": "staff"}}, {"model": "app.staff", "pk": "NV005", "fields": {"ho_ten": "Vũ Đức Hòa", "ngay_sinh": "1993-09-19", "so_dien_thoai": "0967890123", "role": "staff"}}, {"model": "app.staff", "pk": "NV006", "fields": {"ho_ten": "Nguyễn Hữu Tài", "ngay_sinh": "1988-07-01", "so_dien_thoai": "0943217890", "role": "staff"}}, {"model": "app.staff", "pk": "NV007", "fields": {"ho_ten": "Đỗ Thị Hạnh", "ngay_sinh": "1996-11-11", "so_dien_thoai": "0978912345", "role": "staff"}}, {"model": "app.staff", "pk": "NV008", "fields": {"ho_ten": "Lê Thị Mai", "ngay_sinh": "1991-05-05", "so_dien_thoai": "0923456789", "role": "staff"}}, {"model": "app.account", "pk": 1, "fields": {"username": "nvan", "password": "pbkdf2_sha256$1000000$Qad0dg6qlzELvuOtbXuFAM$tk9eXyijnGnLDY0wtFX4uOZsor+LR2VEUH4L8O1Lwqc=", "email": "nvan@example.com", "ma_nhan_vien": "NV001"}}, {"model": "app.account", "pk": 2, "fields": {"username": "tbinh", "password": "pbkdf2_sha256$1000000$dQ0SybddL7pv0DOqDEBBhQ$S0gltr7HX1PjWXxt1MsllbjSRnpVt7yc5sBqcBZuvAI=", "email": "tbinh@example.com", "ma_nhan_vien": "NV002"}}, {"model": "app.account", "pk": 3, "fields": {"username": "lcuong", "password": "pbkdf2_sha256$1000000$socOznyUFXy11XvhIxu3Al$TtQOkf39ANMLhdZHEdQ7iAs2Xc7vHXj/iWEYUXTsMjs=", "email": "lcuong@example.com", "ma_nhan_vien": "NV003"}}, {"model": "app.account", "pk": 4, "fields": {"username": "pdung", "password": "pbkdf2_sha256$1000000$2gsoSlRP2bw3rXGt9IVxK0$abjY9MvIsnAU7YumMStmQnCDT/Eg75Zmey9k07WD2Vg=", "email": "pdung@example.com", "ma_nhan_vien": "NV004"}}, {"model": "app.account", "pk": 5, "fields": {"username": "dhoa", "password": "pbkdf2_sha256$1000000$TaJbvuk57SHjOpoCKfzctQ$rFhsQB13HhI87V7Ol2zrxgXz8DCDi4CeTwasCioLdQk=", "email": "dhoa@example.com", "ma_nhan_vien": "NV005"}}, {"model": "app.account", "pk": 6, "fields": {"username": "htai", "password": "pbkdf2_sha256$1000000$JahEr36pOTQwlmrHqctPQN$Ms3/GsAVIs33ZIVt+MWU41vwX18tTo5GBSjPKYgZuN4=", "email": "htai@example.com", "ma_nhan_vien": "NV006"}}, {"model": "app.account", "pk": 7, "fields": {"username": "thanh", "password": "pbkdf2_sha256$1000000$Skpm3UpSPWZ2VOBBrnPdZi$9JiXgklq9LuI0v1eOcCM1v9G2mX6TI0+OQd73tixqDc=", "email": "thanh@example.com", "ma_nhan_vien": "NV007"}}, {"model": "app.account", "pk": 8, "fields": {"username": "lmai", "password": "pbkdf2_sha256$1000000$cOmtkqCoW03Pp9aoEZao2D$PDPBQ/mMG0XHBgQVoxBsbMfs6Hud8QUmDAhPwxf2XIg=", "email": "lmai@example.com", "ma_nhan_vien": "NV008"}}, {"model": "app.account", "pk": 9, "fields": {"username": "tnam_admin", "password": "pbkdf2_sha256$1000000$5k65wTwmQxWP8UmMV7uSao$m/xsIAVkgdZETbeOvmYgzf0tU5nJy+jaYMcDJ0VU1v0=", "email": "tnam.admin@example.com", "ma_nhan_vien": "AD001"}}, {"model": "app.account", "pk": 10, "fields": {"username": "ttrang_admin", "password": "pbkdf2_sha256$1000000$1BPPnWZWA4iP4k9rGumdSv$nalJV9fAAdQ58NPTCAQtMLhAN8/7y5EPNELLH33QeqM=", "email": "ttrang.admin@example.com", "ma_nhan_vien": "AD002"}}, {"model": "app.roomtype", "pk": "RT01", "fields": {"ten_loai": "Phòng đơn nhỏ", "gia_phong": "250000.00"}}, {"model": "app.roomtype", "pk": "RT02", "fields": {"ten_loai": "Phòng đơn lớn", "gia_phong": "302000.00"}}, {"model": "app.roomtype", "pk": "RT03", "fields": {"ten_loai": "Phòng đôi nhỏ", "gia_phong": "400000.00"}}, {"model": "app.roomtype", "pk": "RT04", "fields": {"ten_loai": "Phòng đôi lớn", "gia_phong": "470000.00"}}, {"model": "app.roomtype", "pk": "RT05", "fields": {"ten_loai": "Phòng gia đình - 5 giường", "gia_phong": "800000.00"}}, {"model": "app.roomtype", "pk": "RT06", "fields": {"ten_loai": "Phòng VIP 1", "gia_phong": "900000.00"}}, {"model": "app.roomtype", "pk": "RT07", "fields": {"ten_loai": "Phòng VIP 2", "gia_phong": "1330460.00"}}, {"model": "app.room", "pk": "F1-101", "fields": {"ma_loai": "RT01", "so_phong": "101", "trang_thai": "Trống"}}, {"model": "app.room", "pk": "F1-102", "fields": {"ma_loai": "RT01", "so_phong": "102", "trang_thai": "Trống"}}, {"model": "app.room", "pk": "F1-103", "fields": {"ma_loai": "RT02", "so_phong": "103", "trang_thai": "Trống"}}, {"model": "app.room", "pk": "F1-104", "fields": {"ma_loai": "RT02", "so_phong": "104", "trang_thai": "Trống"}}, {"model": "app.room", "pk": "F1-105", "fields": {"ma_loai": "RT05", "so_phong": "105", "trang_thai": "Trống"}}, {"model": "app.room", "pk": "F1-106", "fields": {"ma_loai": "RT06", "so_phong": "106", "trang_thai": "Trống"}}, {"model": "app.room", "pk": "F1-107", "fields": {"ma_loai": "RT07", "so_phong": "107", "trang_thai": "Trống"}}, {"model": "app.room", "pk": "F2-101", "fields": {"ma_loai": "RT01", "so_phong": "101", "trang_thai": "Trống"}}, {"model": "app.room", "pk": "F2-102", "fields": {"ma_loai": "RT01", "so_phong": "102", "trang_thai": "Trống"}}, {"model": "app.room", "pk": "F2-103", "fields": {"ma_loai": "RT02", "so_phong": "103", "trang_thai": "Trống"}}, {"model": "app.room", "pk": "F2-104", "fields": {"ma_loai": "RT02", "so_phong": "104", "trang_thai": "Trống"}}, {"model": "app.room", "pk": "F2-105", "fields": {"ma_loai": "RT05", "so_phong": "105", "trang_thai": "Trống"}}, {"model": "app.room", "pk": "F2-106", "fields": {"ma_loai": "RT06", "so_phong": "106", "trang_thai": "Trống"}}, {"model": "app.room", "pk": "F2-107", "fields": {"ma_loai": "RT07", "so_phong": "107", "trang_thai": "Trống"}}, {"model": "app.room", "pk": "F3-101", "fields": {"ma_loai": "RT01", "so_phong": "101", "trang_thai": "Trống"}}, {"model": "app.room", "pk": "F3-102", "fields": {"ma_loai": "RT01", "so_phong": "102", "trang_thai": "Trống"}}, {"model": "app.room", "pk": "F3-103", "fields": {"ma_loai": "RT02", "so_phong": "103", "trang_thai": "Trống"}}, {"model": "app.room", "pk": "F3-104", "fields": {"ma_loai": "RT02", "so_phong": "104", "trang_thai": "Trống"}}, {"model": "app.room", "pk": "F3-105", "fields": {"ma_loai": "RT05", "so_phong": "105", "trang_thai": "Trống"}}, {"model": "app.room", "pk": "F3-106", "fields": {"ma_loai": "RT06", "so_phong": "106", "trang_thai": "Trống"}}, {"model": "app.room", "pk": "F3-107", "fields": {"ma_loai": "RT07", "so_phong": "107", "trang_thai": "Trống"}}, {"model": "app.customer", "pk": "KH001", "fields": {"ten_khach_hang": "Nguyễn Thị An", "dia_chi": "Hà Nội", "so_dien_thoai": "0912345678"}}, {"model": "app.customer", "pk": "KH002", "fields": {"ten_khach_hang": "Trần Văn Bình", "dia_chi": "TP.HCM", "so_dien_thoai": "0934567890"}}, {"model": "app.customer", "pk": "KH003", "fields": {"ten_khach_hang": "Lê Thị Cẩm Vân", "dia_chi": "Đà Nẵng", "so_dien_thoai": "0945678901"}}, {"model": "app.customer", "pk": "KH004", "fields": {"ten_khach_hang": "Phạm Văn Dũng", "dia_chi": "Cần Thơ", "so_dien_thoai": "0967890123"}}, {"model": "app.customer", "pk": "KH005", "fields": {"ten_khach_hang": "Hồ Thị Thu Trang", "dia_chi": "Hải Phòng", "so_dien_thoai": "0978901234"}}, {"model": "app.customer", "pk": "KH006", "fields": {"ten_khach_hang": "Bùi Minh Hoàng", "dia_chi": "Huế", "so_dien_thoai": "0989012345"}}, {"model": "app.customer", "pk": "KH007", "fields": {"ten_khach_hang": "Vũ Thị Hạnh", "dia_chi": "Quảng Ninh", "so_dien_thoai": "0990123456"}}, {"model": "app.customer", "pk": "KH008", "fields": {"ten_khach_hang": "Đỗ Văn Khánh", "dia_chi": "Thanh Hóa", "so_dien_thoai": "0901234567"}}, {"model": "app.customer", "pk": "KH009", "fields": {"ten_khach_hang": "Lương Thị Mai", "dia_chi": "Nha Trang", "so_dien_thoai": "0922345678"}}, {"model": "app.customer", "pk": "KH010", "fields": {"ten_khach_hang": "Trịnh Văn Nam", "dia_chi": "Bắc Ninh", "so_dien_thoai": "0933456789"}}, {"model": "app.service", "pk": "DV001", "fields": {"ten_dich_vu": "Giặt ủi", "gia_dich_vu": "56000.00"}}, {"model": "app.service", "pk": "DV002", "fields": {"ten_dich_vu": "Ăn sáng buffet", "gia_dich_vu": "100000.00"}}, {"model": "app.service", "pk": "DV003", "fields": {"ten_dich_vu": "Đưa đón sân bay", "gia_dich_vu": "240000.00"}}, {"model": "app.service", "pk": "DV004", "fields": {"ten_dich_vu": "Spa thư giãn", "gia_dich_vu": "160000.00"}}, {"model": "app.service", "pk": "DV005", "fields": {"ten_dich_vu": "Massage", "gia_dich_vu": "260000.00"}}, {"model": "app.service", "pk": "DV006", "fields": {"ten_dich_vu": "Thuê xe máy", "gia_dich_vu": "120000.00"}}, {"model": "app.service", "pk": "DV007", "fields": {"ten_dich_vu": "Thuê xe đạp", "gia_dich_vu": "66000.00"}}, {"model": "app.service", "pk": "DV008", "fields": {"ten_dich_vu": "Karaoke phòng VIP", "gia_dich_vu": "130000.00"}}, {"model": "app.invoice", "pk": "HD0001", "fields": {"ma_nhan_vien": "NV001", "ngay_lap_hoa_don": "2025-01-25", "trang_thai": "Đã thanh toán", "tong_tien": "8374300.00"}}, {"model": "app.rent", "pk": "TH0001", "fields": {"ma_khach_hang": "KH007", "hoa_don": "HD0001", "ma_nhan_vien": null, "ma_phong": "F3-107", "ngay_thue": "2025-01-21", "ngay_nhan": "2025-01-21", "ngay_tra": "2025-01-26", "trang_thai": "Đã trả"}}, {"model": "app.serviceusage", "pk": "SDDV0001", "fields": {"ma_khach_hang": "KH007", "ma_dich_vu": "DV006", "ma_nhan_vien": "NV008", "so_luong": 2, "ngay_su_dung": "2025-01-21", "status": "Đã thanh toán", "hoa_don": "HD0001"}}, {"model": "app.serviceusage", "pk": "SDDV0002", "fields": {"ma_khach_hang": "KH007", "ma_dich_vu": "DV001", "ma_nhan_vien": "NV002", "so_luong": 2, "ngay_su_dung": "2025-01-22", "status": "Đã thanh toán", "hoa_don": "HD0001"}}, {"model": "app.serviceusage", "pk": "SDDV0003", "fields": {"ma_khach_hang": "KH007", "ma_dich_vu": "DV007", "ma_nhan_vien": "NV004", "so_luong": 5, "ngay_su_dung": "2025-01-21", "status": "Đã thanh toán", "hoa_don": "HD0001"}}, {"model": "app.serviceusage", "pk": "SDDV0004", "fields": {"ma_khach_hang": "KH007", "ma_dich_vu": "DV005", "ma_nhan_vien": "NV005", "so_luong": 4, "ngay_su_dung": "2025-01-22", "status": "Đã thanh toán", "hoa_don": "HD0001"}}]